{
  "curatedAt": "2026-01-17T01:54:51.485Z",
  "totalAnalyzed": 66,
  "totalSelected": 5,
  "newsletter": {
    "leadStory": {
      "title": "'THE EXORCIST' REBOOT SETS MARCH 2027 RELEASE WITH STARS SCARLETT JOHANSSON, JACOBI JUPE",
      "url": "https://www.thewrap.com/creative-content/movies/exorcist-sets-march-2027-release/",
      "timestamp": "2026-01-17T01:54:48.498Z",
      "source": "splash",
      "scores": {
        "impact": 0.5,
        "engagement": 0.6,
        "timeliness": 1,
        "discovery": 0.3,
        "composite": 0.6100000000000001
      }
    },
    "deepDive": [
      {
        "title": "Essential Releases, January 16, 2026",
        "url": "https://daily.bandcamp.com/essential-releases/essential-releases-january-16-2026",
        "timestamp": "15:16",
        "source": "musicReleases",
        "scores": {
          "impact": 0.6,
          "engagement": 0.6,
          "timeliness": 0.2,
          "discovery": 0.3,
          "composite": 0.49
        }
      }
    ],
    "discovery": [
      {
        "title": "Yellowcard Go Back in Time With Good Charlotte for 'Bedroom Posters'",
        "url": "https://www.rollingstone.com/music/music-news/yellowcard-good-charlotte-bedroom-posters-1235500517/",
        "timestamp": "22:03",
        "source": "musicReleases",
        "scores": {
          "impact": 0.5,
          "engagement": 0.5,
          "timeliness": 0.2,
          "discovery": 0.5,
          "composite": 0.44
        }
      }
    ],
    "conversation": [
      {
        "title": "The 3 Best Movies to Watch on Netflix This Weekend",
        "url": "https://www.thewrap.com/creative-content/what-to-watch/3-best-movies-to-watch-on-netflix-this-weekend-jan-16-18/",
        "timestamp": "23:00",
        "source": "automated",
        "scores": {
          "impact": 0.5,
          "engagement": 0.75,
          "timeliness": 0.2,
          "discovery": 0.3,
          "composite": 0.495
        }
      },
      {
        "title": "Dolly Parton's 25 Best Songs: Critics'&#160;Picks",
        "url": "https://www.billboard.com/lists/best-dolly-parton-songs/",
        "timestamp": "00:58",
        "source": "automated",
        "scores": {
          "impact": 0.5,
          "engagement": 0.7,
          "timeliness": 0.2,
          "discovery": 0.3,
          "composite": 0.4800000000000001
        }
      }
    ],
    "wildcard": [
      {
        "title": "'THE EXORCIST' REBOOT SETS MARCH 2027 RELEASE WITH STARS SCARLETT JOHANSSON, JACOBI JUPE",
        "url": "https://www.thewrap.com/creative-content/movies/exorcist-sets-march-2027-release/",
        "timestamp": "2026-01-17T01:54:48.498Z",
        "source": "splash",
        "scores": {
          "impact": 0.5,
          "engagement": 0.6,
          "timeliness": 1,
          "discovery": 0.3,
          "composite": 0.6100000000000001
        }
      }
    ]
  },
  "stories": [
    {
      "title": "'THE EXORCIST' REBOOT SETS MARCH 2027 RELEASE WITH STARS SCARLETT JOHANSSON, JACOBI JUPE",
      "url": "https://www.thewrap.com/creative-content/movies/exorcist-sets-march-2027-release/",
      "timestamp": "2026-01-17T01:54:48.498Z",
      "source": "splash",
      "scores": {
        "impact": 0.5,
        "engagement": 0.6,
        "timeliness": 1,
        "discovery": 0.3,
        "composite": 0.6100000000000001
      }
    },
    {
      "title": "Essential Releases, January 16, 2026",
      "url": "https://daily.bandcamp.com/essential-releases/essential-releases-january-16-2026",
      "timestamp": "15:16",
      "source": "musicReleases",
      "scores": {
        "impact": 0.6,
        "engagement": 0.6,
        "timeliness": 0.2,
        "discovery": 0.3,
        "composite": 0.49
      }
    },
    {
      "title": "Yellowcard Go Back in Time With Good Charlotte for 'Bedroom Posters'",
      "url": "https://www.rollingstone.com/music/music-news/yellowcard-good-charlotte-bedroom-posters-1235500517/",
      "timestamp": "22:03",
      "source": "musicReleases",
      "scores": {
        "impact": 0.5,
        "engagement": 0.5,
        "timeliness": 0.2,
        "discovery": 0.5,
        "composite": 0.44
      }
    },
    {
      "title": "The 3 Best Movies to Watch on Netflix This Weekend",
      "url": "https://www.thewrap.com/creative-content/what-to-watch/3-best-movies-to-watch-on-netflix-this-weekend-jan-16-18/",
      "timestamp": "23:00",
      "source": "automated",
      "scores": {
        "impact": 0.5,
        "engagement": 0.75,
        "timeliness": 0.2,
        "discovery": 0.3,
        "composite": 0.495
      }
    },
    {
      "title": "Dolly Parton's 25 Best Songs: Critics'&#160;Picks",
      "url": "https://www.billboard.com/lists/best-dolly-parton-songs/",
      "timestamp": "00:58",
      "source": "automated",
      "scores": {
        "impact": 0.5,
        "engagement": 0.7,
        "timeliness": 0.2,
        "discovery": 0.3,
        "composite": 0.4800000000000001
      }
    }
  ],
  "metadata": {
    "algorithm": "Quantum Curation v1.0",
    "weights": {
      "impact": 0.4,
      "engagement": 0.3,
      "timeliness": 0.2,
      "discovery": 0.1
    }
  }
}