{
  "curatedAt": "2026-01-14T14:29:34.702Z",
  "totalAnalyzed": 66,
  "totalSelected": 5,
  "newsletter": {
    "leadStory": {
      "title": "BTS TO PLAY 79 SHOWS ON ‘BIGGEST GLOBAL K-POP TOUR OF ALL TIME’",
      "url": "https://musically.com/2026/01/14/bts-to-play-79-shows-on-biggest-global-k-pop-tour-of-all-time/",
      "timestamp": "2026-01-14T14:29:31.691Z",
      "source": "splash",
      "scores": {
        "impact": 0.6,
        "engagement": 0.7,
        "timeliness": 1,
        "discovery": 0.3,
        "composite": 0.6799999999999999
      }
    },
    "deepDive": [
      {
        "title": "BTS TO PLAY 79 SHOWS ON ‘BIGGEST GLOBAL K-POP TOUR OF ALL TIME’",
        "url": "https://musically.com/2026/01/14/bts-to-play-79-shows-on-biggest-global-k-pop-tour-of-all-time/",
        "timestamp": "2026-01-14T14:29:31.691Z",
        "source": "splash",
        "scores": {
          "impact": 0.6,
          "engagement": 0.7,
          "timeliness": 1,
          "discovery": 0.3,
          "composite": 0.6799999999999999
        }
      },
      {
        "title": "Spotify Spotlights Artists, Songwriters to Watch In&#160;2026",
        "url": "https://www.billboard.com/music/music-news/spotify-artists-songwriters-to-watch-in-2026-1236154738/",
        "timestamp": "07:03",
        "source": "musicReleases",
        "scores": {
          "impact": 0.6,
          "engagement": 0.65,
          "timeliness": 0.2,
          "discovery": 0.3,
          "composite": 0.505
        }
      },
      {
        "title": "Skrilla on “6 7,” Kensington, and his new album Z",
        "url": "https://www.thefader.com/2026/01/13/skrilla-67-interview-kensington-z",
        "timestamp": "21:21",
        "source": "musicReleases",
        "scores": {
          "impact": 0.6,
          "engagement": 0.65,
          "timeliness": 0.2,
          "discovery": 0.3,
          "composite": 0.505
        }
      }
    ],
    "discovery": [
      {
        "title": "Fleetwood Mac's \"Landslide\" Makes Hot 100 Debut 51 Years After Release",
        "url": "https://stereogum.com/2485142/fleetwood-macs-landslide-makes-hot-100-debut-51-years-after-release/news/",
        "timestamp": "21:35",
        "source": "musicReleases",
        "scores": {
          "impact": 0.5,
          "engagement": 0.6,
          "timeliness": 0.2,
          "discovery": 0.5,
          "composite": 0.47000000000000003
        }
      }
    ],
    "conversation": [
      {
        "title": "BTS TO PLAY 79 SHOWS ON ‘BIGGEST GLOBAL K-POP TOUR OF ALL TIME’",
        "url": "https://musically.com/2026/01/14/bts-to-play-79-shows-on-biggest-global-k-pop-tour-of-all-time/",
        "timestamp": "2026-01-14T14:29:31.691Z",
        "source": "splash",
        "scores": {
          "impact": 0.6,
          "engagement": 0.7,
          "timeliness": 1,
          "discovery": 0.3,
          "composite": 0.6799999999999999
        }
      },
      {
        "title": "Are You Afraid of the Dark: The Greatest Children's Horror Show Ever?",
        "url": "https://www.joblo.com/are-you-afraid-of-the-dark-the-greatest-childrens-horror-show-ever/",
        "timestamp": "14:00",
        "source": "automated",
        "scores": {
          "impact": 0.5,
          "engagement": 0.7999999999999999,
          "timeliness": 0.2,
          "discovery": 0.3,
          "composite": 0.51
        }
      }
    ],
    "wildcard": [
      {
        "title": "BTS TO PLAY 79 SHOWS ON ‘BIGGEST GLOBAL K-POP TOUR OF ALL TIME’",
        "url": "https://musically.com/2026/01/14/bts-to-play-79-shows-on-biggest-global-k-pop-tour-of-all-time/",
        "timestamp": "2026-01-14T14:29:31.691Z",
        "source": "splash",
        "scores": {
          "impact": 0.6,
          "engagement": 0.7,
          "timeliness": 1,
          "discovery": 0.3,
          "composite": 0.6799999999999999
        }
      }
    ]
  },
  "stories": [
    {
      "title": "BTS TO PLAY 79 SHOWS ON ‘BIGGEST GLOBAL K-POP TOUR OF ALL TIME’",
      "url": "https://musically.com/2026/01/14/bts-to-play-79-shows-on-biggest-global-k-pop-tour-of-all-time/",
      "timestamp": "2026-01-14T14:29:31.691Z",
      "source": "splash",
      "scores": {
        "impact": 0.6,
        "engagement": 0.7,
        "timeliness": 1,
        "discovery": 0.3,
        "composite": 0.6799999999999999
      }
    },
    {
      "title": "Spotify Spotlights Artists, Songwriters to Watch In&#160;2026",
      "url": "https://www.billboard.com/music/music-news/spotify-artists-songwriters-to-watch-in-2026-1236154738/",
      "timestamp": "07:03",
      "source": "musicReleases",
      "scores": {
        "impact": 0.6,
        "engagement": 0.65,
        "timeliness": 0.2,
        "discovery": 0.3,
        "composite": 0.505
      }
    },
    {
      "title": "Skrilla on “6 7,” Kensington, and his new album Z",
      "url": "https://www.thefader.com/2026/01/13/skrilla-67-interview-kensington-z",
      "timestamp": "21:21",
      "source": "musicReleases",
      "scores": {
        "impact": 0.6,
        "engagement": 0.65,
        "timeliness": 0.2,
        "discovery": 0.3,
        "composite": 0.505
      }
    },
    {
      "title": "Fleetwood Mac's \"Landslide\" Makes Hot 100 Debut 51 Years After Release",
      "url": "https://stereogum.com/2485142/fleetwood-macs-landslide-makes-hot-100-debut-51-years-after-release/news/",
      "timestamp": "21:35",
      "source": "musicReleases",
      "scores": {
        "impact": 0.5,
        "engagement": 0.6,
        "timeliness": 0.2,
        "discovery": 0.5,
        "composite": 0.47000000000000003
      }
    },
    {
      "title": "Are You Afraid of the Dark: The Greatest Children's Horror Show Ever?",
      "url": "https://www.joblo.com/are-you-afraid-of-the-dark-the-greatest-childrens-horror-show-ever/",
      "timestamp": "14:00",
      "source": "automated",
      "scores": {
        "impact": 0.5,
        "engagement": 0.7999999999999999,
        "timeliness": 0.2,
        "discovery": 0.3,
        "composite": 0.51
      }
    }
  ],
  "metadata": {
    "algorithm": "Quantum Curation v1.0",
    "weights": {
      "impact": 0.4,
      "engagement": 0.3,
      "timeliness": 0.2,
      "discovery": 0.1
    }
  }
}